{
  "document_date": {
    "month": 12,
    "year": 2025,
    "month_name": "December"
  },
  "table_a_current_sff": [
    {
      "provider_number": "315205",
      "facility_name": "Majestic Center For Rehab & Sub-Acute Care Two Cooper Plaza Camde n",
      "address": "856-342-",
      "city": null,
      "state": "NJ",
      "zip": "08103",
      "phone_number": null,
      "most_recent_inspection": "07/03/2025",
      "met_survey_criteria": "Met",
      "months_as_sff": 10
    },
    {
      "provider_number": "325038",
      "facility_name": "Casa Real",
      "address": "1650",
      "city": "Galisteo Street Santa",
      "state": "NM",
      "zip": "87505",
      "phone_number": null,
      "most_recent_inspection": "09/29/2025",
      "met_survey_criteria": "Not Met",
      "months_as_sff": 5
    },
    {
      "provider_number": "295029",
      "facility_name": "White Pine Care Center",
      "address": "1500",
      "city": "Avenue",
      "state": "NV",
      "zip": "89301",
      "phone_number": null,
      "most_recent_inspection": null,
      "met_survey_criteria": null,
      "months_as_sff": 5
    },
    {
      "provider_number": "335184",
      "facility_name": "Van Duyn Center For Rehabilitation And Nursing",
      "address": "5075",
      "city": "West Seneca Turnpike Syracus",
      "state": "NY",
      "zip": "13215",
      "phone_number": null,
      "most_recent_inspection": null,
      "met_survey_criteria": null,
      "months_as_sff": 2
    },
    {
      "provider_number": "335082",
      "facility_name": "Waterview Heights Rehabilitation And Nursing Center",
      "address": "425",
      "city": "Beach Avenue Rochest",
      "state": "NY",
      "zip": "14612",
      "phone_number": null,
      "most_recent_inspection": "05/09/2025",
      "met_survey_criteria": "Not Met",
      "months_as_sff": 23
    },
    {
      "provider_number": "335744",
      "facility_name": "Grand Manor Nursing & Rehabilitation Center",
      "address": "700",
      "city": "White Plains Road Bronx",
      "state": "NY",
      "zip": "10473",
      "phone_number": null,
      "most_recent_inspection": "05/29/2025",
      "met_survey_criteria": "Not Met",
      "months_as_sff": 32
    },
    {
      "provider_number": "365952",
      "facility_name": "Ridgewood Manor",
      "address": "3231",
      "city": "Manley Road Maume",
      "state": "OH",
      "zip": "43537",
      "phone_number": null,
      "most_recent_inspection": "05/08/2025",
      "met_survey_criteria": "Met",
      "months_as_sff": 29
    },
    {
      "provider_number": "365826",
      "facility_name": "Continuing Healthcare Of Cuyahoga Falls",
      "address": "300",
      "city": "East Bath Road Cuyahoga Falls",
      "state": "OH",
      "zip": "44223",
      "phone_number": null,
      "most_recent_inspection": "06/12/2025",
      "met_survey_criteria": "Not Met",
      "months_as_sff": 21
    },
    {
      "provider_number": "365754",
      "facility_name": "Majestic Care Of Columbus Llc",
      "address": "44",
      "city": null,
      "state": "OH",
      "zip": "43222",
      "phone_number": null,
      "most_recent_inspection": "06/12/2025",
      "met_survey_criteria": "Met",
      "months_as_sff": 29
    },
    {
      "provider_number": "365022",
      "facility_name": "Atrium Nursing And Rehabilitation",
      "address": "1301",
      "city": "North Monroe Drive Xeni",
      "state": "OH",
      "zip": "45385",
      "phone_number": null,
      "most_recent_inspection": "06/26/2025",
      "met_survey_criteria": "Met",
      "months_as_sff": 19
    },
    {
      "provider_number": "375253",
      "facility_name": "Clinton Therapy & Living Center",
      "address": "2316",
      "city": "Modelle Clinton",
      "state": "OK",
      "zip": "73601",
      "phone_number": null,
      "most_recent_inspection": "06/05/2025",
      "met_survey_criteria": "Met",
      "months_as_sff": 7
    },
    {
      "provider_number": "385091",
      "facility_name": "Hearthstone Nursing & Rehabilitation Center",
      "address": "2901",
      "city": null,
      "state": "OR",
      "zip": "97504",
      "phone_number": null,
      "most_recent_inspection": "05/23/2025",
      "met_survey_criteria": "Met",
      "months_as_sff": 22
    },
    {
      "provider_number": "395892",
      "facility_name": "Kadima Rehabilitation & Nursing At Latrobe",
      "address": "576",
      "city": "Fred Rogers Drive Latrob",
      "state": "PA",
      "zip": "15650",
      "phone_number": null,
      "most_recent_inspection": "05/20/2025",
      "met_survey_criteria": "Met",
      "months_as_sff": 12
    },
    {
      "provider_number": "395985",
      "facility_name": "Midtown Oaks Health & Rehab Center",
      "address": "1020",
      "city": "Green Avenue Altoon",
      "state": "PA",
      "zip": "16601",
      "phone_number": null,
      "most_recent_inspection": "09/11/2025",
      "met_survey_criteria": "Met",
      "months_as_sff": 6
    },
    {
      "provider_number": "395751",
      "facility_name": "Rochester Residence And Care Center",
      "address": "174",
      "city": "Virginia Avenue Rochest",
      "state": "PA",
      "zip": "15074",
      "phone_number": null,
      "most_recent_inspection": "09/19/2025",
      "met_survey_criteria": "Not Met",
      "months_as_sff": 6
    },
    {
      "provider_number": "395929",
      "facility_name": "Ridgeview Healthcare & Rehab Center",
      "address": "200",
      "city": "Pennsylvania Avenue Shenandoa",
      "state": "PA",
      "zip": "17976",
      "phone_number": null,
      "most_recent_inspection": "10/23/2025",
      "met_survey_criteria": "Met",
      "months_as_sff": 37
    },
    {
      "provider_number": "415084",
      "facility_name": "Elmhurst Rehabilitation And Healthcare Center",
      "address": "50",
      "city": "Maude Street Providenc",
      "state": "RI",
      "zip": "02908",
      "phone_number": null,
      "most_recent_inspection": "07/31/2025",
      "met_survey_criteria": "Met",
      "months_as_sff": 39
    },
    {
      "provider_number": "435129",
      "facility_name": "Dells Nursing And Rehab Center Inc",
      "address": "1400",
      "city": "Thresher",
      "state": "SD",
      "zip": "57022",
      "phone_number": null,
      "most_recent_inspection": "06/26/2025",
      "met_survey_criteria": "Met",
      "months_as_sff": 28
    },
    {
      "provider_number": "445139",
      "facility_name": "Midtown Center For Health And Rehabilitation",
      "address": "141",
      "city": null,
      "state": "TN",
      "zip": "38104",
      "phone_number": null,
      "most_recent_inspection": "09/04/2025",
      "met_survey_criteria": "Met",
      "months_as_sff": 18
    },
    {
      "provider_number": "675112",
      "facility_name": "Coral Rehabilitation And Nursing Of Arlington",
      "address": "1112",
      "city": "Gibbins",
      "state": "TX",
      "zip": "76011",
      "phone_number": null,
      "most_recent_inspection": null,
      "met_survey_criteria": null,
      "months_as_sff": 7
    },
    {
      "provider_number": "675879",
      "facility_name": "Terrell Healthcare Center",
      "address": "204",
      "city": null,
      "state": "TX",
      "zip": "75160",
      "phone_number": null,
      "most_recent_inspection": null,
      "met_survey_criteria": null,
      "months_as_sff": 4
    },
    {
      "provider_number": "675595",
      "facility_name": "Harmony Care At Beaumont",
      "address": "2660",
      "city": "Brickyard",
      "state": "TX",
      "zip": "77703",
      "phone_number": null,
      "most_recent_inspection": null,
      "met_survey_criteria": null,
      "months_as_sff": 2
    },
    {
      "provider_number": "455725",
      "facility_name": "Oakmont Healthcare And Rehabilitation Of Humble",
      "address": "8450",
      "city": "Will Clayton Pkwy Humbl",
      "state": "TX",
      "zip": "77338",
      "phone_number": null,
      "most_recent_inspection": null,
      "met_survey_criteria": null,
      "months_as_sff": 5
    },
    {
      "provider_number": "675918",
      "facility_name": "Gracy Woods Nursing Center Metric Blvd Austi n",
      "address": "78758",
      "city": null,
      "state": "TX",
      "zip": "12021",
      "phone_number": null,
      "most_recent_inspection": "07/31/2025",
      "met_survey_criteria": "Not Met",
      "months_as_sff": 8
    },
    {
      "provider_number": "675085",
      "facility_name": "Paradigm At Woodwind Lakes",
      "address": "7215",
      "city": "Windfern",
      "state": "TX",
      "zip": "77040",
      "phone_number": null,
      "most_recent_inspection": "08/14/2025",
      "met_survey_criteria": "Met",
      "months_as_sff": 18
    },
    {
      "provider_number": "465117",
      "facility_name": "South Ogden Post-Acute",
      "address": "5540",
      "city": "South",
      "state": "UT",
      "zip": "84405",
      "phone_number": null,
      "most_recent_inspection": "08/21/2025",
      "met_survey_criteria": "Met",
      "months_as_sff": 30
    },
    {
      "provider_number": "495193",
      "facility_name": "Henrico Health & Rehabilitation Center",
      "address": "561",
      "city": "North Airport Drive Highland Springs",
      "state": "VA",
      "zip": "23075",
      "phone_number": null,
      "most_recent_inspection": "07/22/2025",
      "met_survey_criteria": "Not Met",
      "months_as_sff": 10
    },
    {
      "provider_number": "475020",
      "facility_name": "Premier Rehab And Healthcare At Berlin",
      "address": "98",
      "city": "Hospitality Drive Barre",
      "state": "VT",
      "zip": "05641",
      "phone_number": null,
      "most_recent_inspection": "08/06/2025",
      "met_survey_criteria": "Not Met",
      "months_as_sff": 25
    },
    {
      "provider_number": "505491",
      "facility_name": "Everett Center",
      "address": "1919",
      "city": null,
      "state": "WA",
      "zip": "98204",
      "phone_number": null,
      "most_recent_inspection": "08/29/2025",
      "met_survey_criteria": "Not Met",
      "months_as_sff": 19
    },
    {
      "provider_number": "525262",
      "facility_name": "Fort Atkinson Care Center",
      "address": "430",
      "city": "Wilcox",
      "state": "WI",
      "zip": "53538",
      "phone_number": null,
      "most_recent_inspection": "04/17/2025",
      "met_survey_criteria": "Not Met",
      "months_as_sff": 10
    },
    {
      "provider_number": "525074",
      "facility_name": "Madison Health And Rehabilitation Center",
      "address": "110",
      "city": "Belmont",
      "state": "WI",
      "zip": "53714",
      "phone_number": null,
      "most_recent_inspection": "08/26/2025",
      "met_survey_criteria": "Met",
      "months_as_sff": 15
    },
    {
      "provider_number": "515086",
      "facility_name": "Beckley Healthcare Center",
      "address": "100",
      "city": "Heartland Drive Beckl",
      "state": "WV",
      "zip": "25801",
      "phone_number": null,
      "most_recent_inspection": null,
      "met_survey_criteria": "Met",
      "months_as_sff": 11
    },
    {
      "provider_number": "535022",
      "facility_name": "The Legacy Living And Rehabilitation Center",
      "address": "1000",
      "city": null,
      "state": "WY",
      "zip": "82716",
      "phone_number": null,
      "most_recent_inspection": "09/11/2025",
      "met_survey_criteria": "Not Met",
      "months_as_sff": 2
    },
    {
      "provider_number": "015217",
      "facility_name": "Birmingham Nursing And Rehabilitation Ctr Llc",
      "address": "1000",
      "city": "Dugan Avenue Birmingha",
      "state": "AL",
      "zip": "35214",
      "phone_number": null,
      "most_recent_inspection": "08/29/2024",
      "met_survey_criteria": null,
      "months_as_sff": 19
    },
    {
      "provider_number": "015144",
      "facility_name": "The Healthcare Center At Buck Creek",
      "address": "850",
      "city": null,
      "state": "AL",
      "zip": "35007",
      "phone_number": null,
      "most_recent_inspection": "12/19/2022",
      "met_survey_criteria": null,
      "months_as_sff": 48
    },
    {
      "provider_number": "045287",
      "facility_name": "Bear Creek Healthcare Llc",
      "address": "322",
      "city": "West Collin Raye Drive",
      "state": "AR",
      "zip": "71832",
      "phone_number": null,
      "most_recent_inspection": "11/07/2024",
      "met_survey_criteria": null,
      "months_as_sff": 10
    },
    {
      "provider_number": "045259",
      "facility_name": "The Blossoms At Woodland Hills Rehab & Nursing Cen",
      "address": "8701",
      "city": "Riley Drive Little Rock",
      "state": "AR",
      "zip": "72205",
      "phone_number": null,
      "most_recent_inspection": "01/13/2023",
      "met_survey_criteria": null,
      "months_as_sff": 22
    },
    {
      "provider_number": "045432",
      "facility_name": "The Springs Of Barrow",
      "address": "2600",
      "city": "John Barrow Road Little Rock",
      "state": "AR",
      "zip": "72204",
      "phone_number": null,
      "most_recent_inspection": "01/04/2024",
      "met_survey_criteria": null,
      "months_as_sff": 34
    },
    {
      "provider_number": "045438",
      "facility_name": "Trinity Village Medical Center",
      "address": "6400",
      "city": "Trinity Drive Pine Bluff",
      "state": "AR",
      "zip": "71603",
      "phone_number": null,
      "most_recent_inspection": "09/11/2025",
      "met_survey_criteria": null,
      "months_as_sff": 10
    },
    {
      "provider_number": "035175",
      "facility_name": "Desert Peak Care Center",
      "address": "8825",
      "city": "South",
      "state": "AZ",
      "zip": "85042",
      "phone_number": null,
      "most_recent_inspection": "12/07/2023",
      "met_survey_criteria": null,
      "months_as_sff": 24
    },
    {
      "provider_number": "035146",
      "facility_name": "Life Care Center Of Paradise Valley",
      "address": "4065",
      "city": "East Bell Road Phoeni",
      "state": "AZ",
      "zip": "85032",
      "phone_number": null,
      "most_recent_inspection": null,
      "met_survey_criteria": null,
      "months_as_sff": 10
    },
    {
      "provider_number": "056078",
      "facility_name": "Alta View Post Acute",
      "address": "831",
      "city": null,
      "state": "CA",
      "zip": "90057",
      "phone_number": null,
      "most_recent_inspection": "09/16/2024",
      "met_survey_criteria": null,
      "months_as_sff": 31
    },
    {
      "provider_number": "555776",
      "facility_name": "Gridley Post Acute",
      "address": "246",
      "city": "Spruce Street Gridley",
      "state": "CA",
      "zip": "95948",
      "phone_number": null,
      "most_recent_inspection": "04/15/2024",
      "met_survey_criteria": null,
      "months_as_sff": 23
    },
    {
      "provider_number": "056435",
      "facility_name": "Hyde Park Healthcare Center",
      "address": "6520",
      "city": "West Blvd. Los Angeles",
      "state": "CA",
      "zip": "90043",
      "phone_number": null,
      "most_recent_inspection": "09/12/2024",
      "met_survey_criteria": null,
      "months_as_sff": 33
    },
    {
      "provider_number": "555772",
      "facility_name": "Joshua Tree Post Acute",
      "address": "8515",
      "city": "Cholla Ave Yucca Valley",
      "state": "CA",
      "zip": "92284",
      "phone_number": null,
      "most_recent_inspection": "10/10/2024",
      "met_survey_criteria": null,
      "months_as_sff": 23
    },
    {
      "provider_number": "055412",
      "facility_name": "Vacaville Ranch Post Acute",
      "address": "101",
      "city": null,
      "state": "CA",
      "zip": "95688",
      "phone_number": null,
      "most_recent_inspection": "01/30/2025",
      "met_survey_criteria": null,
      "months_as_sff": 31
    },
    {
      "provider_number": "065232",
      "facility_name": "Atlas Post Acute",
      "address": "2611",
      "city": "Jones Ave Puebl",
      "state": "CO",
      "zip": "81004",
      "phone_number": null,
      "most_recent_inspection": "01/30/2025",
      "met_survey_criteria": null,
      "months_as_sff": 23
    },
    {
      "provider_number": "065152",
      "facility_name": "Sundance Skilled Nursing And Rehabilitation",
      "address": "2612",
      "city": null,
      "state": "CO",
      "zip": "80904",
      "phone_number": null,
      "most_recent_inspection": "02/01/2023",
      "met_survey_criteria": null,
      "months_as_sff": 27
    },
    {
      "provider_number": "085012",
      "facility_name": "Regency Healthcare & Rehab Center",
      "address": "801",
      "city": null,
      "state": "DE",
      "zip": "19806",
      "phone_number": null,
      "most_recent_inspection": "07/18/2025",
      "met_survey_criteria": null,
      "months_as_sff": 35
    },
    {
      "provider_number": "106074",
      "facility_name": "Aviata At Kissimmee Gardens",
      "address": "1120",
      "city": null,
      "state": "FL",
      "zip": "34741",
      "phone_number": null,
      "most_recent_inspection": "07/25/2024",
      "met_survey_criteria": null,
      "months_as_sff": 22
    },
    {
      "provider_number": "105262",
      "facility_name": "Blue Lake Post Acute",
      "address": "991",
      "city": null,
      "state": "FL",
      "zip": "32724",
      "phone_number": null,
      "most_recent_inspection": "01/19/2023",
      "met_survey_criteria": null,
      "months_as_sff": 22
    },
    {
      "provider_number": "105638",
      "facility_name": "Parklands Care Center And Rehab",
      "address": "1000",
      "city": null,
      "state": "FL",
      "zip": "32601",
      "phone_number": null,
      "most_recent_inspection": "12/05/2023",
      "met_survey_criteria": null,
      "months_as_sff": 11
    },
    {
      "provider_number": "105234",
      "facility_name": "Rehabilitation And Healthcare Center Of Tampa",
      "address": "4411",
      "city": null,
      "state": "FL",
      "zip": "33614",
      "phone_number": null,
      "most_recent_inspection": "06/23/2025",
      "met_survey_criteria": null,
      "months_as_sff": 14
    },
    {
      "provider_number": "105407",
      "facility_name": "Siesta Key Health And Rehabilitation Center",
      "address": "4602",
      "city": "Northgate Court Sarasot",
      "state": "FL",
      "zip": "34234",
      "phone_number": null,
      "most_recent_inspection": null,
      "met_survey_criteria": null,
      "months_as_sff": 11
    },
    {
      "provider_number": "115654",
      "facility_name": "Harmony Health And Rehabilitation",
      "address": "176",
      "city": "Lincoln Ave Fitzgerald",
      "state": "GA",
      "zip": "31750",
      "phone_number": null,
      "most_recent_inspection": "03/05/2024",
      "met_survey_criteria": null,
      "months_as_sff": 11
    },
    {
      "provider_number": "115561",
      "facility_name": "Meadowbrook Health And Rehab",
      "address": "4608",
      "city": "Lawrenceville Highway Tucke",
      "state": "GA",
      "zip": "30084",
      "phone_number": null,
      "most_recent_inspection": "02/07/2025",
      "met_survey_criteria": null,
      "months_as_sff": 11
    },
    {
      "provider_number": "115635",
      "facility_name": "River Brook Healthcare Center",
      "address": "390",
      "city": "Sweat Street Homerville",
      "state": "GA",
      "zip": "31634",
      "phone_number": null,
      "most_recent_inspection": "03/20/2023",
      "met_survey_criteria": null,
      "months_as_sff": 48
    },
    {
      "provider_number": "125056",
      "facility_name": "Hale Makua Health Services",
      "address": "1540",
      "city": "Lower Main Street Wailuku",
      "state": "HI",
      "zip": "96793",
      "phone_number": null,
      "most_recent_inspection": "07/09/2024",
      "met_survey_criteria": null,
      "months_as_sff": 19
    },
    {
      "provider_number": "125019",
      "facility_name": "The Care Center Of Honolulu",
      "address": "1900",
      "city": "Bachelot Street Honolul",
      "state": "HI",
      "zip": "96817",
      "phone_number": null,
      "most_recent_inspection": "11/23/2022",
      "met_survey_criteria": null,
      "months_as_sff": 31
    },
    {
      "provider_number": "165478",
      "facility_name": "Arbor Court",
      "address": "701",
      "city": "East Mapleleaf Drive Mount Pleasant",
      "state": "IA",
      "zip": "52641",
      "phone_number": null,
      "most_recent_inspection": "05/01/2025",
      "met_survey_criteria": null,
      "months_as_sff": 26
    },
    {
      "provider_number": "135146",
      "facility_name": "Cascadia Of Boise",
      "address": "6000",
      "city": null,
      "state": "ID",
      "zip": "83704",
      "phone_number": null,
      "most_recent_inspection": "09/20/2024",
      "met_survey_criteria": null,
      "months_as_sff": 15
    },
    {
      "provider_number": "135135",
      "facility_name": "Life Care Center Of Post Falls",
      "address": "460",
      "city": "North Garden Plaza Court Post Falls",
      "state": "ID",
      "zip": "83854",
      "phone_number": null,
      "most_recent_inspection": "06/01/2023",
      "met_survey_criteria": null,
      "months_as_sff": 13
    },
    {
      "provider_number": "135116",
      "facility_name": "Royal Plaza Health And Rehabilitation Of Cascadia",
      "address": "2870",
      "city": "Juniper Drive Lewisto",
      "state": "ID",
      "zip": "83501",
      "phone_number": null,
      "most_recent_inspection": "06/02/2025",
      "met_survey_criteria": null,
      "months_as_sff": 8
    },
    {
      "provider_number": "145180",
      "facility_name": "Aperion Care Chicago Heights",
      "address": "490",
      "city": "West",
      "state": "IL",
      "zip": "60411",
      "phone_number": null,
      "most_recent_inspection": "02/24/2025",
      "met_survey_criteria": null,
      "months_as_sff": 39
    },
    {
      "provider_number": "145950",
      "facility_name": "Generations At Rock Island",
      "address": "2545",
      "city": null,
      "state": "IL",
      "zip": "61201",
      "phone_number": null,
      "most_recent_inspection": "03/06/2023",
      "met_survey_criteria": null,
      "months_as_sff": 33
    },
    {
      "provider_number": "145333",
      "facility_name": "West Suburban Nursing & Rehab Center",
      "address": "311",
      "city": "Edgewater Drive Bloomingdale",
      "state": "IL",
      "zip": "60108",
      "phone_number": null,
      "most_recent_inspection": "06/27/2023",
      "met_survey_criteria": null,
      "months_as_sff": 16
    },
    {
      "provider_number": "155826",
      "facility_name": "Evergreen Crossing And The Lofts",
      "address": "5404",
      "city": "Georgetown Road Indianapoli",
      "state": "IN",
      "zip": "46254",
      "phone_number": null,
      "most_recent_inspection": "02/15/2024",
      "met_survey_criteria": null,
      "months_as_sff": 26
    },
    {
      "provider_number": "155222",
      "facility_name": "Kokomo Healthcare Center",
      "address": "429",
      "city": null,
      "state": "IN",
      "zip": "46902",
      "phone_number": null,
      "most_recent_inspection": "11/25/2024",
      "met_survey_criteria": null,
      "months_as_sff": 14
    },
    {
      "provider_number": "155491",
      "facility_name": "Majestic Care Of Connersville",
      "address": "1029",
      "city": null,
      "state": "IN",
      "zip": "47331",
      "phone_number": null,
      "most_recent_inspection": "09/04/2024",
      "met_survey_criteria": null,
      "months_as_sff": 15
    },
    {
      "provider_number": "155389",
      "facility_name": "Westpark A Waters Community",
      "address": "1316",
      "city": null,
      "state": "IN",
      "zip": "46222",
      "phone_number": null,
      "most_recent_inspection": "05/23/2023",
      "met_survey_criteria": null,
      "months_as_sff": 11
    },
    {
      "provider_number": "175335",
      "facility_name": "Advena Living Of Cherryvale",
      "address": "1001",
      "city": null,
      "state": "KS",
      "zip": "67335",
      "phone_number": null,
      "most_recent_inspection": "03/21/2024",
      "met_survey_criteria": null,
      "months_as_sff": 11
    },
    {
      "provider_number": "185262",
      "facility_name": "Madison Health And Rehabilitation Center",
      "address": "131",
      "city": "Meadowlark Drive Richmo",
      "state": "KY",
      "zip": "40475",
      "phone_number": null,
      "most_recent_inspection": "12/05/2024",
      "met_survey_criteria": null,
      "months_as_sff": 21
    },
    {
      "provider_number": "195454",
      "facility_name": "Winnfield Nursing And Rehabilitation Center, Llc",
      "address": "915",
      "city": null,
      "state": "LA",
      "zip": "71483",
      "phone_number": null,
      "most_recent_inspection": "11/03/2023",
      "met_survey_criteria": null,
      "months_as_sff": 20
    },
    {
      "provider_number": "225063",
      "facility_name": "Marlborough Hills Rehabilitation & Hlth Care Ctr",
      "address": "121",
      "city": "Northboro Road Marlboroug",
      "state": "MA",
      "zip": "01752",
      "phone_number": null,
      "most_recent_inspection": "12/30/2022",
      "met_survey_criteria": null,
      "months_as_sff": 20
    },
    {
      "provider_number": "225747",
      "facility_name": "Somerset Ridge Center",
      "address": "455",
      "city": "Brayton Avenue Somers",
      "state": "MA",
      "zip": "02726",
      "phone_number": null,
      "most_recent_inspection": "11/12/2024",
      "met_survey_criteria": null,
      "months_as_sff": 22
    },
    {
      "provider_number": "225488",
      "facility_name": "Tremont Rehabilitation & Skilled Care Center",
      "address": "605",
      "city": "Main Street Wareh",
      "state": "MA",
      "zip": "02571",
      "phone_number": null,
      "most_recent_inspection": "02/12/2025",
      "met_survey_criteria": null,
      "months_as_sff": 14
    },
    {
      "provider_number": "215094",
      "facility_name": "Westminster Healthcare Center",
      "address": "1234",
      "city": "Washington Road Westminste",
      "state": "MD",
      "zip": "21157",
      "phone_number": null,
      "most_recent_inspection": "04/10/2025",
      "met_survey_criteria": null,
      "months_as_sff": 20
    },
    {
      "provider_number": "205077",
      "facility_name": "Augusta Center For Health & Rehabilitation, Llc",
      "address": "188",
      "city": "Eastern Ave August",
      "state": "ME",
      "zip": "04330",
      "phone_number": null,
      "most_recent_inspection": "01/24/2025",
      "met_survey_criteria": null,
      "months_as_sff": 10
    },
    {
      "provider_number": "205120",
      "facility_name": "Waterville Center For Health And Rehab",
      "address": "7",
      "city": "Highwood",
      "state": "ME",
      "zip": "04901",
      "phone_number": null,
      "most_recent_inspection": "08/25/2023",
      "met_survey_criteria": null,
      "months_as_sff": 9
    },
    {
      "provider_number": "235532",
      "facility_name": "Ashley Healthcare Center",
      "address": "103",
      "city": "West Wallace Street Ashle",
      "state": "MI",
      "zip": "48806",
      "phone_number": null,
      "most_recent_inspection": "02/26/2025",
      "met_survey_criteria": null,
      "months_as_sff": 21
    },
    {
      "provider_number": "235654",
      "facility_name": "The Orchards At Lapeer",
      "address": "239",
      "city": "South Main Street Lapeer",
      "state": "MI",
      "zip": "48446",
      "phone_number": null,
      "most_recent_inspection": "05/12/2023",
      "met_survey_criteria": null,
      "months_as_sff": 30
    },
    {
      "provider_number": "235503",
      "facility_name": "The Villa At Parkridge",
      "address": "28",
      "city": null,
      "state": "MI",
      "zip": "48198",
      "phone_number": null,
      "most_recent_inspection": "03/14/2024",
      "met_survey_criteria": null,
      "months_as_sff": 29
    },
    {
      "provider_number": "245544",
      "facility_name": "Victory Health & Rehabilitation Center",
      "address": "512",
      "city": null,
      "state": "MN",
      "zip": "55430",
      "phone_number": null,
      "most_recent_inspection": "01/31/2025",
      "met_survey_criteria": null,
      "months_as_sff": 58
    }
  ],
  "table_b_graduated": [
    {
      "provider_number": "535026",
      "facility_name": "Big Horn Rehabilitation And Care Center",
      "address": "1851",
      "city": "Big Horn Ave Sherida",
      "state": "WY",
      "zip": "82801",
      "phone_number": null,
      "most_recent_inspection": "03/05/2025",
      "met_survey_criteria": null,
      "months_as_sff": 20
    },
    {
      "provider_number": "535025",
      "facility_name": "Polaris Rehabilitation And Care Center",
      "address": "2700",
      "city": null,
      "state": "WY",
      "zip": "82001",
      "phone_number": null,
      "most_recent_inspection": "07/10/2023",
      "met_survey_criteria": null,
      "months_as_sff": 5
    },
    {
      "provider_number": "165344",
      "facility_name": "Aspire Of Gowrie",
      "address": "1808",
      "city": "Main Street Gowri",
      "state": "IA",
      "zip": "50543",
      "phone_number": null,
      "most_recent_inspection": "07/24/2025",
      "met_survey_criteria": null,
      "months_as_sff": 22
    },
    {
      "provider_number": "155857",
      "facility_name": "Tranquility Nursing And Rehab",
      "address": "3640",
      "city": null,
      "state": "IN",
      "zip": "46205",
      "phone_number": null,
      "most_recent_inspection": "07/14/2025",
      "met_survey_criteria": null,
      "months_as_sff": 7
    },
    {
      "provider_number": "175172",
      "facility_name": "Excel Healthcare And Rehab Topeka",
      "address": "2515",
      "city": null,
      "state": "KS",
      "zip": "66614",
      "phone_number": null,
      "most_recent_inspection": "03/07/2025",
      "met_survey_criteria": null,
      "months_as_sff": 24
    },
    {
      "provider_number": "235187",
      "facility_name": "Mission Point Nursing & Physical Rehabilitation Center O Dequindre Madison Heights",
      "address": "48071",
      "city": null,
      "state": "MI",
      "zip": "31155",
      "phone_number": null,
      "most_recent_inspection": "09/12/2025",
      "met_survey_criteria": null,
      "months_as_sff": 18
    },
    {
      "provider_number": "265857",
      "facility_name": "Liberty Health And Wellness",
      "address": "2201",
      "city": "Glenn Hendren",
      "state": "MO",
      "zip": "64068",
      "phone_number": null,
      "most_recent_inspection": "03/07/2025",
      "met_survey_criteria": null,
      "months_as_sff": 35
    },
    {
      "provider_number": "345008",
      "facility_name": "The Citadel At Myers Park, Llc",
      "address": "300",
      "city": "Providence Road Charlott",
      "state": "NC",
      "zip": "28207",
      "phone_number": null,
      "most_recent_inspection": "03/07/2025",
      "met_survey_criteria": null,
      "months_as_sff": 14
    }
  ],
  "table_c_no_longer_participating": [
    {
      "provider_number": "675764",
      "facility_name": "Spring Branch Transitional Care Center",
      "address": "1615",
      "city": "Hillendahl",
      "state": "TX",
      "zip": "77055",
      "phone_number": null,
      "most_recent_inspection": "03/13/2025",
      "met_survey_criteria": null,
      "months_as_sff": 6
    },
    {
      "provider_number": "015406",
      "facility_name": "ARABELLA HEALTH & WELLNESS OF GRAND BAY HIGHWAY",
      "address": "90 WEST GRAND BAY",
      "city": null,
      "state": "AL",
      "zip": "13750",
      "phone_number": null,
      "most_recent_inspection": null,
      "met_survey_criteria": null,
      "months_as_sff": 2
    },
    {
      "provider_number": "015420",
      "facility_name": "CUMBERLAND HEALTH AND REHAB HIGHWAY",
      "address": "277 BRIDGEPOR",
      "city": null,
      "state": "AL",
      "zip": "47065",
      "phone_number": null,
      "most_recent_inspection": null,
      "met_survey_criteria": null,
      "months_as_sff": 14
    },
    {
      "provider_number": "015133",
      "facility_name": "MAGNOLIA RIDGE",
      "address": "420 DEAN DRIVE GARDENDAL",
      "city": null,
      "state": "AL",
      "zip": "35071",
      "phone_number": null,
      "most_recent_inspection": null,
      "met_survey_criteria": null,
      "months_as_sff": 2
    },
    {
      "provider_number": "015019",
      "facility_name": "MERRY WOOD LODGE",
      "address": "280 HEBRON ROAD ELMOR",
      "city": null,
      "state": "MT",
      "zip": "36025",
      "phone_number": null,
      "most_recent_inspection": null,
      "met_survey_criteria": null,
      "months_as_sff": 10
    },
    {
      "provider_number": "015408",
      "facility_name": "WALKER REHABILITATION CENTER, INC",
      "address": "350 NORTHEAST",
      "city": null,
      "state": "AL",
      "zip": "35549",
      "phone_number": null,
      "most_recent_inspection": null,
      "met_survey_criteria": null,
      "months_as_sff": 8
    },
    {
      "provider_number": "045143",
      "facility_name": "CONCORDIA NURSING & REHAB, LLC",
      "address": "7 PROFESSIONAL DRIVE BELLA VISTA",
      "city": null,
      "state": "AR",
      "zip": "72714",
      "phone_number": null,
      "most_recent_inspection": null,
      "met_survey_criteria": null,
      "months_as_sff": 2
    },
    {
      "provider_number": "045435",
      "facility_name": "JAMESTOWN NURSING AND REHAB, LLC",
      "address": "2001 HAMPTON PLACE ROGE RS",
      "city": null,
      "state": "AR",
      "zip": "72758",
      "phone_number": null,
      "most_recent_inspection": null,
      "met_survey_criteria": null,
      "months_as_sff": 5
    },
    {
      "provider_number": "045341",
      "facility_name": "MEADOWVIEW HEALTHCARE AND REHAB",
      "address": "825 NORTH GASKILL HUNTSVILL",
      "city": null,
      "state": "AR",
      "zip": "72740",
      "phone_number": null,
      "most_recent_inspection": null,
      "met_survey_criteria": null,
      "months_as_sff": 9
    },
    {
      "provider_number": "045379",
      "facility_name": "PINE BLUFF TRANSITIONAL CARE",
      "address": "6810 SOUTH HAZEL STREET PINE BLUFF",
      "city": null,
      "state": "AR",
      "zip": "71603",
      "phone_number": null,
      "most_recent_inspection": null,
      "met_survey_criteria": null,
      "months_as_sff": 22
    },
    {
      "provider_number": "045456",
      "facility_name": "PINK BUD HOME FOR THE GOLDEN YEARS",
      "address": "400 SO COKER GREENW OOD",
      "city": null,
      "state": "AR",
      "zip": "72936",
      "phone_number": null,
      "most_recent_inspection": null,
      "met_survey_criteria": null,
      "months_as_sff": 3
    },
    {
      "provider_number": "035242",
      "facility_name": "DR GUY GORMAN SR CARE HOME HIGHWAY",
      "address": "191",
      "city": null,
      "state": "AZ",
      "zip": "86503",
      "phone_number": null,
      "most_recent_inspection": null,
      "met_survey_criteria": null,
      "months_as_sff": null
    },
    {
      "provider_number": "035016",
      "facility_name": "HANDMAKER HOME FOR THE AGING",
      "address": "2221 NORTH ROSEMONT BOULEVARD TUCSO",
      "city": null,
      "state": "AZ",
      "zip": "85712",
      "phone_number": null,
      "most_recent_inspection": null,
      "met_survey_criteria": null,
      "months_as_sff": 1
    },
    {
      "provider_number": "035217",
      "facility_name": "REHAB AT SCOTTSDALE VILLAGE SQUARE",
      "address": "2620 NORTH",
      "city": null,
      "state": "AZ",
      "zip": "85257",
      "phone_number": null,
      "most_recent_inspection": null,
      "met_survey_criteria": null,
      "months_as_sff": 9
    },
    {
      "provider_number": "035099",
      "facility_name": "SANDSTONE OF TUCSON REHAB CENTRE",
      "address": "2900 EAST MILBER STREET TUCSO",
      "city": null,
      "state": "AZ",
      "zip": "85714",
      "phone_number": null,
      "most_recent_inspection": null,
      "met_survey_criteria": null,
      "months_as_sff": 2
    },
    {
      "provider_number": "035254",
      "facility_name": "WINSLOW CAMPUS OF CARE",
      "address": "826 WEST DESMOND STREET WINSLOW",
      "city": null,
      "state": "AZ",
      "zip": "86047",
      "phone_number": null,
      "most_recent_inspection": null,
      "met_survey_criteria": null,
      "months_as_sff": 9
    },
    {
      "provider_number": "555456",
      "facility_name": "ANTELOPE VALLEY CARE CENTER NORTH",
      "address": "15TH",
      "city": null,
      "state": "CA",
      "zip": "44567",
      "phone_number": null,
      "most_recent_inspection": null,
      "met_survey_criteria": null,
      "months_as_sff": 9
    },
    {
      "provider_number": "555579",
      "facility_name": "ARARAT NURSING FACILITY MISSION HILLS ROAD MISSION HILLS",
      "address": "91345",
      "city": null,
      "state": "CA",
      "zip": "15099",
      "phone_number": null,
      "most_recent_inspection": null,
      "met_survey_criteria": null,
      "months_as_sff": 9
    },
    {
      "provider_number": "055539",
      "facility_name": "ARTESIA CHRISTIAN HOME INC. E.",
      "address": "183RD ST ARTESIA",
      "city": null,
      "state": "CA",
      "zip": "11614",
      "phone_number": null,
      "most_recent_inspection": null,
      "met_survey_criteria": null,
      "months_as_sff": 7
    },
    {
      "provider_number": "055559",
      "facility_name": "BAY CREST CARE CENTER",
      "address": "3750 GARNET STREET TORRANC",
      "city": null,
      "state": "CA",
      "zip": "90503",
      "phone_number": null,
      "most_recent_inspection": null,
      "met_survey_criteria": null,
      "months_as_sff": 2
    },
    {
      "provider_number": "055461",
      "facility_name": "CALIFORNIA POST ACUTE",
      "address": "909",
      "city": null,
      "state": "CA",
      "zip": "90006",
      "phone_number": null,
      "most_recent_inspection": null,
      "met_survey_criteria": null,
      "months_as_sff": 20
    },
    {
      "provider_number": "055052",
      "facility_name": "CALIFORNIA POST-ACUTE CARE",
      "address": "3615",
      "city": null,
      "state": "CA",
      "zip": "90262",
      "phone_number": null,
      "most_recent_inspection": null,
      "met_survey_criteria": null,
      "months_as_sff": 2
    },
    {
      "provider_number": "056043",
      "facility_name": "COLONIAL CARE CENTER",
      "address": "1913",
      "city": null,
      "state": "CA",
      "zip": "90802",
      "phone_number": null,
      "most_recent_inspection": null,
      "met_survey_criteria": null,
      "months_as_sff": 5
    },
    {
      "provider_number": "055077",
      "facility_name": "CORAL COVE POST ACUTE",
      "address": "1730 GRAND AVE LONG BEACH",
      "city": null,
      "state": "CA",
      "zip": "90804",
      "phone_number": null,
      "most_recent_inspection": null,
      "met_survey_criteria": null,
      "months_as_sff": 53
    },
    {
      "provider_number": "055932",
      "facility_name": "FOUR SEASONS HEALTHCARE & WELLNESS CENTER, LP",
      "address": "5335 LAUREL CANYON",
      "city": null,
      "state": "CA",
      "zip": "91607",
      "phone_number": null,
      "most_recent_inspection": null,
      "met_survey_criteria": null,
      "months_as_sff": 2
    },
    {
      "provider_number": "055862",
      "facility_name": "GOLDEN ROSE CARE CENTER",
      "address": "1899",
      "city": null,
      "state": "CA",
      "zip": "91103",
      "phone_number": null,
      "most_recent_inspection": null,
      "met_survey_criteria": null,
      "months_as_sff": 6
    },
    {
      "provider_number": "056063",
      "facility_name": "INFINITY CARE OF EAST LOS ANGELES",
      "address": "101",
      "city": null,
      "state": "CA",
      "zip": "90033",
      "phone_number": null,
      "most_recent_inspection": null,
      "met_survey_criteria": null,
      "months_as_sff": 2
    },
    {
      "provider_number": "056431",
      "facility_name": "INLAND VALLEY CARE AND REHABILITATION CENTER",
      "address": "250",
      "city": null,
      "state": "CA",
      "zip": "91768",
      "phone_number": null,
      "most_recent_inspection": null,
      "met_survey_criteria": null,
      "months_as_sff": 41
    },
    {
      "provider_number": "555583",
      "facility_name": "MACLAY HEALTHCARE CENTER MACLAY STREET SYLMA R",
      "address": "91342",
      "city": null,
      "state": "CA",
      "zip": "12831",
      "phone_number": null,
      "most_recent_inspection": null,
      "met_survey_criteria": null,
      "months_as_sff": 20
    },
    {
      "provider_number": "555115",
      "facility_name": "MAJESTIC MOUNTAIN CARE CENTER HIGHWAY",
      "address": "49 OAKHURS",
      "city": null,
      "state": "CA",
      "zip": "40131",
      "phone_number": null,
      "most_recent_inspection": null,
      "met_survey_criteria": null,
      "months_as_sff": 1
    },
    {
      "provider_number": "555854",
      "facility_name": "MESA GLEN CARE CENTER",
      "address": "638",
      "city": null,
      "state": "CA",
      "zip": "91740",
      "phone_number": null,
      "most_recent_inspection": null,
      "met_survey_criteria": null,
      "months_as_sff": 4
    },
    {
      "provider_number": "056039",
      "facility_name": "MIRAGE POST ACUTE",
      "address": "15TH ST",
      "city": null,
      "state": "CA",
      "zip": "44445",
      "phone_number": null,
      "most_recent_inspection": null,
      "met_survey_criteria": null,
      "months_as_sff": 10
    },
    {
      "provider_number": "056031",
      "facility_name": "NEW VISTA NURSING AND REHABILITATION CENTER",
      "address": "8647 FENWICK",
      "city": null,
      "state": "ND",
      "zip": "91040",
      "phone_number": null,
      "most_recent_inspection": null,
      "met_survey_criteria": null,
      "months_as_sff": 3
    },
    {
      "provider_number": "056259",
      "facility_name": "NORTHVINE POSTACUTE CARE",
      "address": "446 ARROWOOD DR SANTA ROSA",
      "city": null,
      "state": "CA",
      "zip": "95407",
      "phone_number": null,
      "most_recent_inspection": null,
      "met_survey_criteria": null,
      "months_as_sff": 2
    },
    {
      "provider_number": "555852",
      "facility_name": "PARK AVENUE HEALTHCARE & WELLNESS CENTER",
      "address": "1550 NORTH PARK AVENUE POMON",
      "city": null,
      "state": "CA",
      "zip": "91768",
      "phone_number": null,
      "most_recent_inspection": null,
      "met_survey_criteria": null,
      "months_as_sff": 6
    },
    {
      "provider_number": "055858",
      "facility_name": "RANCHO SECO CARE CENTER",
      "address": "144",
      "city": null,
      "state": "CA",
      "zip": "95632",
      "phone_number": null,
      "most_recent_inspection": null,
      "met_survey_criteria": null,
      "months_as_sff": 4
    },
    {
      "provider_number": "555808",
      "facility_name": "SANTA MONICA REHABILITATION CENTER",
      "address": "1338",
      "city": null,
      "state": "CA",
      "zip": "90404",
      "phone_number": null,
      "most_recent_inspection": null,
      "met_survey_criteria": null,
      "months_as_sff": 17
    },
    {
      "provider_number": "555117",
      "facility_name": "SKYLINE HEALTHCARE CENTER -",
      "address": "3032 ROWENA AVE LOS ANGELES",
      "city": null,
      "state": "LA",
      "zip": "90039",
      "phone_number": null,
      "most_recent_inspection": null,
      "met_survey_criteria": null,
      "months_as_sff": 3
    },
    {
      "provider_number": "056488",
      "facility_name": "SUNNYSIDE NURSING CENTER S. VERMONT AVE TORRANC E",
      "address": "90502",
      "city": null,
      "state": "CA",
      "zip": "22617",
      "phone_number": null,
      "most_recent_inspection": null,
      "met_survey_criteria": null,
      "months_as_sff": 3
    },
    {
      "provider_number": "056367",
      "facility_name": "THE REHABILITATION CENTER OF NORTH HILLS",
      "address": "9655 SEPULVEDA BOULEVARD NORTH HILLS",
      "city": null,
      "state": "CA",
      "zip": "91343",
      "phone_number": null,
      "most_recent_inspection": null,
      "met_survey_criteria": null,
      "months_as_sff": 25
    },
    {
      "provider_number": "056206",
      "facility_name": "UNIVERSITY PARK HEALTHCARE CENTER",
      "address": "230",
      "city": null,
      "state": "CA",
      "zip": "90011",
      "phone_number": null,
      "most_recent_inspection": null,
      "met_survey_criteria": null,
      "months_as_sff": 3
    },
    {
      "provider_number": "555781",
      "facility_name": "VILLA DEL RIO",
      "address": "7002 GAGE AVENUE BELL GARDENS",
      "city": null,
      "state": "CA",
      "zip": "90201",
      "phone_number": null,
      "most_recent_inspection": null,
      "met_survey_criteria": null,
      "months_as_sff": 2
    },
    {
      "provider_number": "056066",
      "facility_name": "WOODLAND CARE CENTER",
      "address": "7120 CORBIN",
      "city": null,
      "state": "CA",
      "zip": "91335",
      "phone_number": null,
      "most_recent_inspection": null,
      "met_survey_criteria": null,
      "months_as_sff": 3
    },
    {
      "provider_number": "065248",
      "facility_name": "OAKWOOD CARE AND REHABILITATION",
      "address": "5301",
      "city": null,
      "state": "CO",
      "zip": "80226",
      "phone_number": null,
      "most_recent_inspection": null,
      "met_survey_criteria": null,
      "months_as_sff": 2
    },
    {
      "provider_number": "065278",
      "facility_name": "PELICAN POINTE HEALTH AND REHABILITATION CENTER",
      "address": "710",
      "city": null,
      "state": "CO",
      "zip": "80550",
      "phone_number": null,
      "most_recent_inspection": null,
      "met_survey_criteria": null,
      "months_as_sff": 2
    }
  ],
  "table_d_candidates": [
    {
      "provider_number": "465152",
      "facility_name": "BELLA TERRA ST GEORGE",
      "address": "178 SOUTH",
      "city": null,
      "state": "UT",
      "zip": "84790",
      "phone_number": null,
      "most_recent_inspection": null,
      "met_survey_criteria": null,
      "months_as_sff": 7
    },
    {
      "provider_number": "465088",
      "facility_name": "MISSION AT ALPINE REHABILITATION CENTER",
      "address": "25 EAST ALPINE DRIVE PLEASANT GROVE",
      "city": null,
      "state": "UT",
      "zip": "84062",
      "phone_number": null,
      "most_recent_inspection": null,
      "met_survey_criteria": null,
      "months_as_sff": 2
    },
    {
      "provider_number": "465086",
      "facility_name": "MOUNTAIN VIEW HEALTH SERVICES",
      "address": "5865 SOUTH WASATCH DRIVE OGDE",
      "city": null,
      "state": "UT",
      "zip": "84403",
      "phone_number": null,
      "most_recent_inspection": null,
      "met_survey_criteria": null,
      "months_as_sff": 72
    },
    {
      "provider_number": "465137",
      "facility_name": "RED CLIFFS HEALTH AND REHAB",
      "address": "1745 EAST",
      "city": null,
      "state": "UT",
      "zip": "84790",
      "phone_number": null,
      "most_recent_inspection": null,
      "met_survey_criteria": null,
      "months_as_sff": 8
    },
    {
      "provider_number": "495362",
      "facility_name": "ASHLAND NURSING AND REHABILITATION",
      "address": "906 THOMPSON STREET ASHLAN",
      "city": null,
      "state": "VA",
      "zip": "23005",
      "phone_number": null,
      "most_recent_inspection": null,
      "met_survey_criteria": null,
      "months_as_sff": 2
    },
    {
      "provider_number": "495150",
      "facility_name": "BIRCHWOOD PARK REHABILITATION",
      "address": "340 LYNN SHORES DRIVE VIRGINIA BEACH",
      "city": null,
      "state": "VA",
      "zip": "23452",
      "phone_number": null,
      "most_recent_inspection": null,
      "met_survey_criteria": null,
      "months_as_sff": 6
    },
    {
      "provider_number": "495211",
      "facility_name": "MOUNT VERNON HEALTHCARE CENTER",
      "address": "8111 TISWELL DRIVE ALEXANDRI",
      "city": null,
      "state": "VA",
      "zip": "22306",
      "phone_number": null,
      "most_recent_inspection": null,
      "met_survey_criteria": null,
      "months_as_sff": 29
    },
    {
      "provider_number": "495417",
      "facility_name": "MOUNTAIN LAUREL REHABILITATION AND NURSING",
      "address": "514 NORTH MAIN STREET RURAL RETREAT",
      "city": null,
      "state": "VA",
      "zip": "24368",
      "phone_number": null,
      "most_recent_inspection": null,
      "met_survey_criteria": null,
      "months_as_sff": 2
    },
    {
      "provider_number": "495315",
      "facility_name": "WOODSTOCK VALLEY HEALTH AND REHABILITATION",
      "address": "803 SOUTH MAIN ST WOODSTOC",
      "city": null,
      "state": "VA",
      "zip": "22664",
      "phone_number": null,
      "most_recent_inspection": null,
      "met_survey_criteria": null,
      "months_as_sff": 1
    },
    {
      "provider_number": "475027",
      "facility_name": "BENNINGTON HEALTH & REHAB",
      "address": "2 BLACKBERRY LANE BENNINGTO",
      "city": null,
      "state": "VT",
      "zip": "05201",
      "phone_number": null,
      "most_recent_inspection": null,
      "met_survey_criteria": null,
      "months_as_sff": 29
    },
    {
      "provider_number": "475030",
      "facility_name": "ELDERWOOD AT BURLINGTON",
      "address": "98 STARR FARM",
      "city": null,
      "state": "VT",
      "zip": "05408",
      "phone_number": null,
      "most_recent_inspection": null,
      "met_survey_criteria": null,
      "months_as_sff": 30
    },
    {
      "provider_number": "475040",
      "facility_name": "GREEN MOUNTAIN NURSING AND REHABILITATION",
      "address": "475 ETHAN ALLEN AVENUE COLCHESTE",
      "city": null,
      "state": "VT",
      "zip": "05446",
      "phone_number": null,
      "most_recent_inspection": null,
      "met_survey_criteria": null,
      "months_as_sff": 2
    },
    {
      "provider_number": "475025",
      "facility_name": "SPRINGFIELD HEALTH & REHAB",
      "address": "105 CHESTER ROAD SPRINGFIEL",
      "city": null,
      "state": "VT",
      "zip": "05156",
      "phone_number": null,
      "most_recent_inspection": null,
      "met_survey_criteria": null,
      "months_as_sff": 2
    },
    {
      "provider_number": "475019",
      "facility_name": "ST. JOHNSBURY HEALTH & REHAB",
      "address": "1248 HOSPITAL DRIVE SAINT JOHNSBURY",
      "city": null,
      "state": "VT",
      "zip": "05819",
      "phone_number": null,
      "most_recent_inspection": null,
      "met_survey_criteria": null,
      "months_as_sff": 2
    },
    {
      "provider_number": "505319",
      "facility_name": "ALDERWOOD POST ACUTE & REHABILITATION",
      "address": "3701",
      "city": null,
      "state": "WA",
      "zip": "98037",
      "phone_number": null,
      "most_recent_inspection": null,
      "met_survey_criteria": null,
      "months_as_sff": 5
    },
    {
      "provider_number": "505320",
      "facility_name": "COLUMBIA CREST CENTER",
      "address": "1100 EAST NELSON ROAD MOSES LAKE",
      "city": null,
      "state": "WA",
      "zip": "98837",
      "phone_number": null,
      "most_recent_inspection": null,
      "met_survey_criteria": null,
      "months_as_sff": 7
    },
    {
      "provider_number": "505275",
      "facility_name": "COLVILLE HEALTH AND REHABILITATION OF CASCADIA",
      "address": "1000 EAST ELEP STREET COLVILL",
      "city": null,
      "state": "WA",
      "zip": "99114",
      "phone_number": null,
      "most_recent_inspection": null,
      "met_survey_criteria": null,
      "months_as_sff": 3
    },
    {
      "provider_number": "505254",
      "facility_name": "CRYSTAL COVE POST ACUTE",
      "address": "1505 CARPENTER ROAD SE LACE",
      "city": null,
      "state": "WA",
      "zip": "98503",
      "phone_number": null,
      "most_recent_inspection": null,
      "met_survey_criteria": null,
      "months_as_sff": 6
    },
    {
      "provider_number": "505322",
      "facility_name": "SPOKANE HEALTH & REHABILITATION NORTH",
      "address": "6025 ASSEMBLY SPOKA",
      "city": null,
      "state": "NE",
      "zip": "99205",
      "phone_number": null,
      "most_recent_inspection": null,
      "met_survey_criteria": null,
      "months_as_sff": 3
    },
    {
      "provider_number": "525424",
      "facility_name": "ARIA OF BROOKFIELD W BLUEMOUND RD BROOKFIEL D",
      "address": "53045",
      "city": null,
      "state": "WI",
      "zip": "18740",
      "phone_number": null,
      "most_recent_inspection": null,
      "met_survey_criteria": null,
      "months_as_sff": 14
    },
    {
      "provider_number": "525315",
      "facility_name": "CROSSROADS CARE CENTER OF WEYAUWEGA",
      "address": "717",
      "city": null,
      "state": "GA",
      "zip": "54983",
      "phone_number": null,
      "most_recent_inspection": null,
      "met_survey_criteria": null,
      "months_as_sff": 3
    },
    {
      "provider_number": "525069",
      "facility_name": "MAPLEWOOD CENTER",
      "address": "8615",
      "city": null,
      "state": "WI",
      "zip": "53227",
      "phone_number": null,
      "most_recent_inspection": null,
      "met_survey_criteria": null,
      "months_as_sff": 4
    },
    {
      "provider_number": "525730",
      "facility_name": "MEDICAL SUITES AT OAK CREEK (THE)",
      "address": "2700 HONADEL BOULEVARD OAK CREEK",
      "city": null,
      "state": "WI",
      "zip": "53154",
      "phone_number": null,
      "most_recent_inspection": null,
      "met_survey_criteria": null,
      "months_as_sff": 33
    },
    {
      "provider_number": "525321",
      "facility_name": "RIVERDALE HEALTH CARE CENTER",
      "address": "1000",
      "city": null,
      "state": "WI",
      "zip": "53573",
      "phone_number": null,
      "most_recent_inspection": null,
      "met_survey_criteria": null,
      "months_as_sff": 2
    },
    {
      "provider_number": "525371",
      "facility_name": "SILVER SPRINGS HEALTH CARE CENTER",
      "address": "1300 WEST SILVER SPRING DR GLENDAL",
      "city": null,
      "state": "WI",
      "zip": "53209",
      "phone_number": null,
      "most_recent_inspection": null,
      "met_survey_criteria": null,
      "months_as_sff": 23
    },
    {
      "provider_number": "525281",
      "facility_name": "WATERS EDGE HEALTH AND REHABILITATION CENTER",
      "address": "3415",
      "city": null,
      "state": "WI",
      "zip": "53140",
      "phone_number": null,
      "most_recent_inspection": null,
      "met_survey_criteria": null,
      "months_as_sff": 1
    },
    {
      "provider_number": "525688",
      "facility_name": "VETERANS HOME-BOLAND HALL E SPRING ST UNION GROVE WI",
      "address": "53182",
      "city": null,
      "state": "WI",
      "zip": "21425",
      "phone_number": null,
      "most_recent_inspection": null,
      "met_survey_criteria": null,
      "months_as_sff": 1
    },
    {
      "provider_number": "515128",
      "facility_name": "BRIGHTWOOD CENTER",
      "address": "840 LEE ROAD FOLLANSBE",
      "city": null,
      "state": "WV",
      "zip": "26037",
      "phone_number": null,
      "most_recent_inspection": null,
      "met_survey_criteria": null,
      "months_as_sff": 2
    },
    {
      "provider_number": "515087",
      "facility_name": "CEDAR RIDGE CENTER",
      "address": "302 CEDAR RIDGE ROAD SISSONVILL",
      "city": null,
      "state": "WV",
      "zip": "25320",
      "phone_number": null,
      "most_recent_inspection": null,
      "met_survey_criteria": null,
      "months_as_sff": 7
    },
    {
      "provider_number": "515060",
      "facility_name": "HERITAGE CENTER",
      "address": "101-13TH STREET HUNTINGTO",
      "city": null,
      "state": "WV",
      "zip": "25701",
      "phone_number": null,
      "most_recent_inspection": null,
      "met_survey_criteria": null,
      "months_as_sff": 7
    },
    {
      "provider_number": "515049",
      "facility_name": "MORGANTOWN HEIGHTS OF JOURNEY",
      "address": "1379 VAN VOORHIS RD MORGANTO WN",
      "city": null,
      "state": "WV",
      "zip": "26505",
      "phone_number": null,
      "most_recent_inspection": null,
      "met_survey_criteria": null,
      "months_as_sff": 13
    },
    {
      "provider_number": "515140",
      "facility_name": "TRINITY HEALTH CARE OF LOGAN",
      "address": "1000 WEST PARK AVENUE LOGA",
      "city": null,
      "state": "WV",
      "zip": "25601",
      "phone_number": null,
      "most_recent_inspection": null,
      "met_survey_criteria": null,
      "months_as_sff": 3
    },
    {
      "provider_number": "535024",
      "facility_name": "CASPER MOUNTAIN REHABILITATION AND CARE CENTER",
      "address": "4305",
      "city": null,
      "state": "WY",
      "zip": "82601",
      "phone_number": null,
      "most_recent_inspection": null,
      "met_survey_criteria": null,
      "months_as_sff": 7
    },
    {
      "provider_number": "535054",
      "facility_name": "GREEN HOUSE LIVING FOR SHERIDAN",
      "address": "2311 SHIRLEY COVE SHERIDA",
      "city": null,
      "state": "WY",
      "zip": "82801",
      "phone_number": null,
      "most_recent_inspection": null,
      "met_survey_criteria": null,
      "months_as_sff": 5
    },
    {
      "provider_number": "535036",
      "facility_name": "RAWLINS SNF OPERATIONS LLC",
      "address": "542",
      "city": null,
      "state": "WY",
      "zip": "82301",
      "phone_number": null,
      "most_recent_inspection": null,
      "met_survey_criteria": null,
      "months_as_sff": 23
    },
    {
      "provider_number": "535042",
      "facility_name": "SHEPHERD OF THE VALLEY REHABILITATION AND WELLNESS",
      "address": "60 MAGNOLIA ST CASPE",
      "city": null,
      "state": "WY",
      "zip": "82604",
      "phone_number": null,
      "most_recent_inspection": null,
      "met_survey_criteria": null,
      "months_as_sff": 2
    },
    {
      "provider_number": "535040",
      "facility_name": "SUMMIT RIDGE SKILLED NURSING & REHABILITATION",
      "address": "1108 BIRCH STREET DOUGLA",
      "city": null,
      "state": "WY",
      "zip": "82633",
      "phone_number": null,
      "most_recent_inspection": null,
      "met_survey_criteria": null,
      "months_as_sff": 15
    }
  ],
  "summary": {
    "current_sff_count": 83,
    "graduated_count": 8,
    "no_longer_participating_count": 45,
    "candidates_count": 37,
    "total_count": 173
  }
}